whilelang/__init__.py
whilelang/__main__.py
whilelang/base_parser.py
whilelang/const.py
whilelang/errors.py
whilelang/lexer.py
whilelang/main.py
whilelang/nodes.py
whilelang/parser.py
whilelang/token.py
whilelang-0.0.2.data/scripts/while.py
whilelang-0.0.2.dist-info/METADATA
whilelang-0.0.2.dist-info/WHEEL
whilelang-0.0.2.dist-info/top_level.txt
whilelang-0.0.2.dist-info/RECORD
