Metadata-Version: 2.1
Name: whilelang
Version: 0.0.2
Summary: A minimal implementation of the While language
Home-page: https://github.com/Bottersnike/whileland
Author: Bottersnike
Author-email: bottersnike237@gmail.com
License: UNKNOWN
Project-URL: Bug Tracker, https://github.com/Bottersnike/whileland/issues
Platform: UNKNOWN
Classifier: Programming Language :: Python :: 3
Classifier: Programming Language :: Python :: 3.8
Classifier: Operating System :: OS Independent
Requires-Python: >=3.8
